dsalibpy/__init__.py
dsalibpy/arrays.py
dsalibpy/disjoint_sets.py
dsalibpy/graphs.py
dsalibpy/hash_tables.py
dsalibpy/heaps.py
dsalibpy/linked_lists.py
dsalibpy/queues.py
dsalibpy/stacks.py
dsalibpy/trees.py
dsalibpy/tries.py
dsalibpy-0.3.dist-info/METADATA
dsalibpy-0.3.dist-info/WHEEL
dsalibpy-0.3.dist-info/top_level.txt
dsalibpy-0.3.dist-info/RECORD
