Metadata-Version: 2.1
Name: dsalibpy
Version: 0.3
Summary: A library for fundamental and advanced data structures
Home-page: https://github.com/yasho11/Py_dsalib.git
Author: Yashodeep Basnet
Author-email: yyashodeep.basnet@gmail.com
